django_query_optimizer/__init__.py
django_query_optimizer/model_analyzer.py
django_query_optimizer/query_optimizer.py
django_query_optimizer-0.5.0.dist-info/License
django_query_optimizer-0.5.0.dist-info/METADATA
django_query_optimizer-0.5.0.dist-info/WHEEL
django_query_optimizer-0.5.0.dist-info/top_level.txt
django_query_optimizer-0.5.0.dist-info/RECORD
