Metadata-Version: 2.1
Name: django_query_optimizer
Version: 0.5.0
Summary: Automatic optimization of django queries
Home-page: https://github.com/YasinKar/django_query_optimizer
Author: Yasin Karbasi
Author-email: yasinkardev@gmail.com
Classifier: Programming Language :: Python :: 3
Classifier: License :: OSI Approved :: MIT License
Classifier: Operating System :: OS Independent
Requires-Python: >=3.6
License-File: License
Requires-Dist: django
